clion_live_templates_generator/__init__.py
clion_live_templates_generator/main.py
clion_live_templates_generator-1.0.3.dist-info/LICENSE
clion_live_templates_generator-1.0.3.dist-info/METADATA
clion_live_templates_generator-1.0.3.dist-info/WHEEL
clion_live_templates_generator-1.0.3.dist-info/entry_points.txt
clion_live_templates_generator-1.0.3.dist-info/top_level.txt
clion_live_templates_generator-1.0.3.dist-info/RECORD
